mfe/__init__.py
mfe/calibration.py
mfe/feature.py
mfe/from_txt.py
mfe/peak_picking.py
mfe/time.py
mfe/util.py
mfe-0.0.4.dist-info/LICENSE
mfe-0.0.4.dist-info/METADATA
mfe-0.0.4.dist-info/WHEEL
mfe-0.0.4.dist-info/top_level.txt
mfe-0.0.4.dist-info/RECORD
