Metadata-Version: 2.1
Name: mfe
Version: 0.0.4
Summary: Clean mass spectrometry imaging dataset and extract geologically meaningful features
Home-page: https://github.com/weimin-liu/msi_feature_extraction
Author: Weimin Liu
Author-email: wliu@marum.de
Project-URL: Bug Tracker, https://github.com/weimin-liu/msi_feature_extraction/issues
Classifier: Programming Language :: Python :: 3
Classifier: License :: OSI Approved :: MIT License
Classifier: Operating System :: OS Independent
Requires-Python: >=3.5
License-File: LICENSE
Requires-Dist: KDEpy
Requires-Dist: matplotlib
Requires-Dist: numpy
Requires-Dist: pandas
Requires-Dist: scikit-learn
Requires-Dist: scipy
Requires-Dist: setuptools
Requires-Dist: tqdm
Requires-Dist: scikit-image
Requires-Dist: networkx
